{"fragmentation_time": 0.7415098, "payload_size": 512, "total_transmission_time": 394.605, "total_number_of_fragments": 62, "fragments": {"42": {"sending_end": 1101.52, "sending_start": 1078.949, "ack_received": false, "data": " :1234567891", "downlink_enable": false, "FCN": "11010", "fragment_size": 12, "send_time": 22.57092, "ack": "", "receiver_abort_received": false, "timeout": 45, "RULE_ID": "00100000", "abort": false, "rssi": -107, "W": "001", "receiver_abort_message": ""}, "45": {"sending_end": 1175.64, "sending_start": 1153.066, "ack_received": false, "data": " 72344567891", "downlink_enable": false, "FCN": "10111", "fragment_size": 12, "send_time": 22.57349, "ack": "", "receiver_abort_received": false, "timeout": 45, "RULE_ID": "00100000", "abort": false, "rssi": -107, "W": "001", "receiver_abort_message": ""}, "36": {"sending_end": 953.3456, "sending_start": 930.775, "ack_received": false, "data": " \u00068912123456", "downlink_enable": false, "FCN": "00110", "fragment_size": 12, "send_time": 22.57062, "ack": "", "receiver_abort_received": false, "timeout": 45, "RULE_ID": "00100000", "abort": false, "rssi": -107, "W": "000", "receiver_abort_message": ""}, "37": {"sending_end": 978.0186, "sending_start": 955.446, "ack_received": false, "data": " \u00024567891212", "downlink_enable": false, "FCN": "00010", "fragment_size": 12, "send_time": 22.57263, "ack": "", "receiver_abort_received": false, "timeout": 45, "RULE_ID": "00100000", "abort": false, "rssi": -107, "W": "000", "receiver_abort_message": ""}, "34": {"sending_end": 903.9817, "sending_start": 881.4124, "ack_received": false, "data": " \n1212345678", "downlink_enable": false, "FCN": "01010", "fragment_size": 12, "send_time": 22.56922, "ack": "", "receiver_abort_received": false, "timeout": 45, "RULE_ID": "00100000", "abort": false, "rssi": -107, "W": "000", "receiver_abort_message": ""}, "35": {"sending_end": 928.6746, "sending_start": 906.0873, "ack_received": false, "data": " \t9123456345", "downlink_enable": false, "FCN": "01001", "fragment_size": 12, "send_time": 22.58728, "ack": "", "receiver_abort_received": false, "timeout": 45, "RULE_ID": "00100000", "abort": false, "rssi": -107, "W": "000", "receiver_abort_message": ""}, "32": {"sending_end": 854.6276, "sending_start": 832.058, "ack_received": false, "data": " \u00135678912123", "downlink_enable": false, "FCN": "10011", "fragment_size": 12, "send_time": 22.56952, "ack": "", "receiver_abort_received": false, "timeout": 45, "RULE_ID": "00100000", "abort": false, "rssi": -107, "W": "000", "receiver_abort_message": ""}, "33": {"sending_end": 879.3047, "sending_start": 856.7331, "ack_received": false, "data": " \u00115678912345", "downlink_enable": false, "FCN": "10001", "fragment_size": 12, "send_time": 22.57153, "ack": "", "receiver_abort_received": false, "timeout": 45, "RULE_ID": "00100000", "abort": false, "rssi": -107, "W": "000", "receiver_abort_message": ""}, "30": {"sending_end": 805.2108, "sending_start": 741.5399, "ack_received": true, "data": " \u00002345678912", "downlink_enable": true, "FCN": "00000", "fragment_size": 12, "send_time": 63.67084, "ack": "0010000000001110111111101011111100110111011000000000000000000000", "receiver_abort_received": false, "timeout": 45, "RULE_ID": "00100000", "abort": false, "rssi": -107, "W": "000", "receiver_abort_message": ""}, "31": {"sending_end": 829.9597, "sending_start": 807.3896, "ack_received": false, "data": " \u001b9121234567", "downlink_enable": false, "FCN": "11011", "fragment_size": 12, "send_time": 22.57001, "ack": "", "receiver_abort_received": false, "timeout": 45, "RULE_ID": "00100000", "abort": false, "rssi": -107, "W": "000", "receiver_abort_message": ""}, "44": {"sending_end": 1150.931, "sending_start": 1128.361, "ack_received": false, "data": " 83456789121", "downlink_enable": false, "FCN": "11000", "fragment_size": 12, "send_time": 22.56995, "ack": "", "receiver_abort_received": false, "timeout": 45, "RULE_ID": "00100000", "abort": false, "rssi": -107, "W": "001", "receiver_abort_message": ""}, "46": {"sending_end": 1200.345, "sending_start": 1177.775, "ack_received": false, "data": " 62123456789", "downlink_enable": false, "FCN": "10110", "fragment_size": 12, "send_time": 22.56995, "ack": "", "receiver_abort_received": false, "timeout": 45, "RULE_ID": "00100000", "abort": false, "rssi": -107, "W": "001", "receiver_abort_message": ""}, "47": {"sending_end": 1225.113, "sending_start": 1202.542, "ack_received": false, "data": " 51212345678", "downlink_enable": false, "FCN": "10101", "fragment_size": 12, "send_time": 22.57031, "ack": "", "receiver_abort_received": false, "timeout": 45, "RULE_ID": "00100000", "abort": false, "rssi": -107, "W": "001", "receiver_abort_message": ""}, "48": {"sending_end": 1249.826, "sending_start": 1227.254, "ack_received": false, "data": " 49121234567", "downlink_enable": false, "FCN": "10100", "fragment_size": 12, "send_time": 22.5719, "ack": "", "receiver_abort_received": false, "timeout": 45, "RULE_ID": "00100000", "abort": false, "rssi": -107, "W": "001", "receiver_abort_message": ""}, "49": {"sending_end": 1274.539, "sending_start": 1251.969, "ack_received": false, "data": " 38912123456", "downlink_enable": false, "FCN": "10011", "fragment_size": 12, "send_time": 22.57007, "ack": "", "receiver_abort_received": false, "timeout": 45, "RULE_ID": "00100000", "abort": false, "rssi": -107, "W": "001", "receiver_abort_message": ""}, "14": {"sending_end": 368.9836, "sending_start": 346.4132, "ack_received": false, "data": " \u00106789121234", "downlink_enable": false, "FCN": "10000", "fragment_size": 12, "send_time": 22.57041, "ack": "", "receiver_abort_received": false, "timeout": 45, "RULE_ID": "00100000", "abort": false, "rssi": -107, "W": "000", "receiver_abort_message": ""}, "38": {"sending_end": 1002.711, "sending_start": 980.1409, "ack_received": false, "data": " >3456789123", "downlink_enable": false, "FCN": "11110", "fragment_size": 12, "send_time": 22.56976, "ack": "", "receiver_abort_received": false, "timeout": 45, "RULE_ID": "00100000", "abort": false, "rssi": -107, "W": "001", "receiver_abort_message": ""}, "39": {"sending_end": 1027.41, "sending_start": 1004.839, "ack_received": false, "data": " =4567891212", "downlink_enable": false, "FCN": "11101", "fragment_size": 12, "send_time": 22.57037, "ack": "", "receiver_abort_received": false, "timeout": 45, "RULE_ID": "00100000", "abort": false, "rssi": -107, "W": "001", "receiver_abort_message": ""}, "15": {"sending_end": 393.6646, "sending_start": 371.0932, "ack_received": false, "data": " \u000f4567891212", "downlink_enable": false, "FCN": "01111", "fragment_size": 12, "send_time": 22.57144, "ack": "", "receiver_abort_received": false, "timeout": 45, "RULE_ID": "00100000", "abort": false, "rssi": -107, "W": "000", "receiver_abort_message": ""}, "16": {"sending_end": 418.3677, "sending_start": 395.7977, "ack_received": false, "data": " \u000e3456789121", "downlink_enable": false, "FCN": "01110", "fragment_size": 12, "send_time": 22.56998, "ack": "", "receiver_abort_received": false, "timeout": 45, "RULE_ID": "00100000", "abort": false, "rssi": -107, "W": "000", "receiver_abort_message": ""}, "17": {"sending_end": 443.0476, "sending_start": 420.476, "ack_received": false, "data": " \r2345678912", "downlink_enable": false, "FCN": "01101", "fragment_size": 12, "send_time": 22.57169, "ack": "", "receiver_abort_received": false, "timeout": 45, "RULE_ID": "00100000", "abort": false, "rssi": -107, "W": "000", "receiver_abort_message": ""}, "10": {"sending_end": 270.2607, "sending_start": 247.6898, "ack_received": false, "data": " \u00146789121234", "downlink_enable": false, "FCN": "10100", "fragment_size": 12, "send_time": 22.57085, "ack": "", "receiver_abort_received": false, "timeout": 45, "RULE_ID": "00100000", "abort": false, "rssi": -107, "W": "000", "receiver_abort_message": ""}, "11": {"sending_end": 294.9437, "sending_start": 272.3734, "ack_received": false, "data": " \u00135678912123", "downlink_enable": false, "FCN": "10011", "fragment_size": 12, "send_time": 22.57025, "ack": "", "receiver_abort_received": false, "timeout": 45, "RULE_ID": "00100000", "abort": false, "rssi": -107, "W": "000", "receiver_abort_message": ""}, "18": {"sending_end": 467.8046, "sending_start": 445.1637, "ack_received": false, "data": " \u000c1234567891", "downlink_enable": false, "FCN": "01100", "fragment_size": 12, "send_time": 22.6409, "ack": "", "receiver_abort_received": false, "timeout": 45, "RULE_ID": "00100000", "abort": false, "rssi": -107, "W": "000", "receiver_abort_message": ""}, "19": {"sending_end": 492.4926, "sending_start": 469.9228, "ack_received": false, "data": " \u000b2123456789", "downlink_enable": false, "FCN": "01011", "fragment_size": 12, "send_time": 22.56983, "ack": "", "receiver_abort_received": false, "timeout": 45, "RULE_ID": "00100000", "abort": false, "rssi": -107, "W": "000", "receiver_abort_message": ""}, "12": {"sending_end": 319.6276, "sending_start": 297.0559, "ack_received": false, "data": " \u00124567891234", "downlink_enable": false, "FCN": "10010", "fragment_size": 12, "send_time": 22.57169, "ack": "", "receiver_abort_received": false, "timeout": 45, "RULE_ID": "00100000", "abort": false, "rssi": -107, "W": "000", "receiver_abort_message": ""}, "13": {"sending_end": 344.3056, "sending_start": 321.7344, "ack_received": false, "data": " \u00115678912345", "downlink_enable": false, "FCN": "10001", "fragment_size": 12, "send_time": 22.5712, "ack": "", "receiver_abort_received": false, "timeout": 45, "RULE_ID": "00100000", "abort": false, "rssi": -107, "W": "000", "receiver_abort_message": ""}, "50": {"sending_end": 1299.254, "sending_start": 1276.683, "ack_received": false, "data": " 27891212345", "downlink_enable": false, "FCN": "10010", "fragment_size": 12, "send_time": 22.57056, "ack": "", "receiver_abort_received": false, "timeout": 45, "RULE_ID": "00100000", "abort": false, "rssi": -107, "W": "001", "receiver_abort_message": ""}, "51": {"sending_end": 1323.969, "sending_start": 1301.399, "ack_received": false, "data": " 16789123456", "downlink_enable": false, "FCN": "10001", "fragment_size": 12, "send_time": 22.57056, "ack": "", "receiver_abort_received": false, "timeout": 45, "RULE_ID": "00100000", "abort": false, "rssi": -107, "W": "001", "receiver_abort_message": ""}, "52": {"sending_end": 1348.682, "sending_start": 1326.108, "ack_received": false, "data": " 03456789123", "downlink_enable": false, "FCN": "10000", "fragment_size": 12, "send_time": 22.57312, "ack": "", "receiver_abort_received": false, "timeout": 45, "RULE_ID": "00100000", "abort": false, "rssi": -107, "W": "001", "receiver_abort_message": ""}, "53": {"sending_end": 1373.393, "sending_start": 1350.822, "ack_received": false, "data": " /4567349121", "downlink_enable": false, "FCN": "01111", "fragment_size": 12, "send_time": 22.57056, "ack": "", "receiver_abort_received": false, "timeout": 45, "RULE_ID": "00100000", "abort": false, "rssi": -107, "W": "001", "receiver_abort_message": ""}, "54": {"sending_end": 1398.105, "sending_start": 1375.535, "ack_received": false, "data": " .2345678912", "downlink_enable": false, "FCN": "01110", "fragment_size": 12, "send_time": 22.57007, "ack": "", "receiver_abort_received": false, "timeout": 45, "RULE_ID": "00100000", "abort": false, "rssi": -107, "W": "001", "receiver_abort_message": ""}, "55": {"sending_end": 1422.815, "sending_start": 1400.244, "ack_received": false, "data": " -3456789123", "downlink_enable": false, "FCN": "01101", "fragment_size": 12, "send_time": 22.57019, "ack": "", "receiver_abort_received": false, "timeout": 45, "RULE_ID": "00100000", "abort": false, "rssi": -107, "W": "001", "receiver_abort_message": ""}, "56": {"sending_end": 1447.604, "sending_start": 1424.964, "ack_received": false, "data": " ,4567891212", "downlink_enable": false, "FCN": "01100", "fragment_size": 12, "send_time": 22.63965, "ack": "", "receiver_abort_received": false, "timeout": 45, "RULE_ID": "00100000", "abort": false, "rssi": -107, "W": "001", "receiver_abort_message": ""}, "57": {"sending_end": 1472.325, "sending_start": 1449.755, "ack_received": false, "data": " +3456789121", "downlink_enable": false, "FCN": "01011", "fragment_size": 12, "send_time": 22.56995, "ack": "", "receiver_abort_received": false, "timeout": 45, "RULE_ID": "00100000", "abort": false, "rssi": -107, "W": "001", "receiver_abort_message": ""}, "58": {"sending_end": 1528.205, "sending_start": 1474.471, "ack_received": true, "data": " ?23", "downlink_enable": true, "FCN": "11111", "fragment_size": 4, "send_time": 53.73389, "ack": "0010000000001111111111111111111110111111011000000000000000000000", "receiver_abort_received": false, "timeout": 45, "RULE_ID": "00100000", "abort": false, "rssi": -109, "W": "001", "receiver_abort_message": ""}, "59": {"sending_end": 1552.952, "sending_start": 1530.38, "ack_received": false, "data": " \t9123456345", "downlink_enable": false, "FCN": "01001", "fragment_size": 12, "send_time": 22.57117, "ack": "", "receiver_abort_received": false, "timeout": 45, "RULE_ID": "00100000", "abort": false, "rssi": -109, "W": "000", "receiver_abort_message": ""}, "27": {"sending_end": 690.0176, "sending_start": 667.4473, "ack_received": false, "data": " \u00035678912123", "downlink_enable": false, "FCN": "00011", "fragment_size": 12, "send_time": 22.57031, "ack": "", "receiver_abort_received": false, "timeout": 45, "RULE_ID": "00100000", "abort": false, "rssi": -107, "W": "000", "receiver_abort_message": ""}, "26": {"sending_end": 665.3227, "sending_start": 642.7531, "ack_received": false, "data": " \u00046789121234", "downlink_enable": false, "FCN": "00100", "fragment_size": 12, "send_time": 22.56958, "ack": "", "receiver_abort_received": false, "timeout": 45, "RULE_ID": "00100000", "abort": false, "rssi": -107, "W": "000", "receiver_abort_message": ""}, "25": {"sending_end": 640.6296, "sending_start": 618.0601, "ack_received": false, "data": " \u00057891212345", "downlink_enable": false, "FCN": "00101", "fragment_size": 12, "send_time": 22.56952, "ack": "", "receiver_abort_received": false, "timeout": 45, "RULE_ID": "00100000", "abort": false, "rssi": -107, "W": "000", "receiver_abort_message": ""}, "24": {"sending_end": 615.9337, "sending_start": 593.3638, "ack_received": false, "data": " \u00068912123456", "downlink_enable": false, "FCN": "00110", "fragment_size": 12, "send_time": 22.56989, "ack": "", "receiver_abort_received": false, "timeout": 45, "RULE_ID": "00100000", "abort": false, "rssi": -107, "W": "000", "receiver_abort_message": ""}, "23": {"sending_end": 591.2466, "sending_start": 568.6751, "ack_received": false, "data": " \u00077341234567", "downlink_enable": false, "FCN": "00111", "fragment_size": 12, "send_time": 22.57141, "ack": "", "receiver_abort_received": false, "timeout": 45, "RULE_ID": "00100000", "abort": false, "rssi": -107, "W": "000", "receiver_abort_message": ""}, "22": {"sending_end": 566.5596, "sending_start": 543.9892, "ack_received": false, "data": " \u00086789123456", "downlink_enable": false, "FCN": "01000", "fragment_size": 12, "send_time": 22.57037, "ack": "", "receiver_abort_received": false, "timeout": 45, "RULE_ID": "00100000", "abort": false, "rssi": -107, "W": "000", "receiver_abort_message": ""}, "21": {"sending_end": 541.8746, "sending_start": 519.3027, "ack_received": false, "data": " \t9123456345", "downlink_enable": false, "FCN": "01001", "fragment_size": 12, "send_time": 22.57184, "ack": "", "receiver_abort_received": false, "timeout": 45, "RULE_ID": "00100000", "abort": false, "rssi": -107, "W": "000", "receiver_abort_message": ""}, "20": {"sending_end": 517.1826, "sending_start": 494.6118, "ack_received": false, "data": " \n1212345678", "downlink_enable": false, "FCN": "01010", "fragment_size": 12, "send_time": 22.5708, "ack": "", "receiver_abort_received": false, "timeout": 45, "RULE_ID": "00100000", "abort": false, "rssi": -107, "W": "000", "receiver_abort_message": ""}, "5": {"sending_end": 146.8606, "sending_start": 124.2882, "ack_received": false, "data": " \u00197891212345", "downlink_enable": false, "FCN": "11001", "fragment_size": 12, "send_time": 22.57241, "ack": "", "receiver_abort_received": false, "timeout": 45, "RULE_ID": "00100000", "abort": false, "rssi": -107, "W": "000", "receiver_abort_message": ""}, "4": {"sending_end": 122.1826, "sending_start": 99.61309, "ack_received": false, "data": " \u001a8912123456", "downlink_enable": false, "FCN": "11010", "fragment_size": 12, "send_time": 22.56953, "ack": "", "receiver_abort_received": false, "timeout": 45, "RULE_ID": "00100000", "abort": false, "rssi": -107, "W": "000", "receiver_abort_message": ""}, "7": {"sending_end": 196.2127, "sending_start": 173.6428, "ack_received": false, "data": " \u00175678912345", "downlink_enable": false, "FCN": "10111", "fragment_size": 12, "send_time": 22.56984, "ack": "", "receiver_abort_received": false, "timeout": 45, "RULE_ID": "00100000", "abort": false, "rssi": -107, "W": "000", "receiver_abort_message": ""}, "6": {"sending_end": 171.5387, "sending_start": 148.9671, "ack_received": false, "data": " \u00186789121234", "downlink_enable": false, "FCN": "11000", "fragment_size": 12, "send_time": 22.57153, "ack": "", "receiver_abort_received": false, "timeout": 45, "RULE_ID": "00100000", "abort": false, "rssi": -107, "W": "000", "receiver_abort_message": ""}, "1": {"sending_end": 48.04769, "sending_start": 25.47735, "ack_received": false, "data": " \u001d2123456789", "downlink_enable": false, "FCN": "11101", "fragment_size": 12, "send_time": 22.57033, "ack": "", "receiver_abort_received": false, "timeout": 45, "RULE_ID": "00100000", "abort": false, "rssi": -107, "W": "000", "receiver_abort_message": ""}, "29": {"sending_end": 739.4176, "sending_start": 716.8425, "ack_received": false, "data": " \u00013456789121", "downlink_enable": false, "FCN": "00001", "fragment_size": 12, "send_time": 22.57514, "ack": "", "receiver_abort_received": false, "timeout": 45, "RULE_ID": "00100000", "abort": false, "rssi": -107, "W": "000", "receiver_abort_message": ""}, "3": {"sending_end": 97.50864, "sending_start": 74.93695, "ack_received": false, "data": " \u001b9121234567", "downlink_enable": false, "FCN": "11011", "fragment_size": 12, "send_time": 22.57169, "ack": "", "receiver_abort_received": false, "timeout": 45, "RULE_ID": "00100000", "abort": false, "rssi": -107, "W": "000", "receiver_abort_message": ""}, "28": {"sending_end": 714.7146, "sending_start": 692.144, "ack_received": false, "data": " \u00024567891212", "downlink_enable": false, "FCN": "00010", "fragment_size": 12, "send_time": 22.57062, "ack": "", "receiver_abort_received": false, "timeout": 45, "RULE_ID": "00100000", "abort": false, "rssi": -107, "W": "000", "receiver_abort_message": ""}, "2": {"sending_end": 72.83157, "sending_start": 50.15884, "ack_received": false, "data": " \u001c1212345678", "downlink_enable": false, "FCN": "11100", "fragment_size": 12, "send_time": 22.67274, "ack": "", "receiver_abort_received": false, "timeout": 45, "RULE_ID": "00100000", "abort": false, "rssi": -107, "W": "000", "receiver_abort_message": ""}, "0": {"sending_end": 23.36762, "sending_start": 0.798455, "ack_received": false, "data": " \u001e1234567891", "downlink_enable": false, "FCN": "11110", "fragment_size": 12, "send_time": 22.56917, "ack": "", "receiver_abort_received": false, "timeout": 45, "RULE_ID": "00100000", "abort": false, "rssi": -107, "W": "000", "receiver_abort_message": ""}, "61": {"sending_end": 1633.202, "sending_start": 1579.685, "ack_received": true, "data": " ?23", "downlink_enable": true, "FCN": "11111", "fragment_size": 4, "send_time": 53.51709, "ack": "0010000000110000000000000000000000000000000000000000000000000000", "receiver_abort_received": false, "timeout": 45, "RULE_ID": "00100000", "abort": false, "rssi": -108, "W": "001", "receiver_abort_message": ""}, "9": {"sending_end": 245.5777, "sending_start": 223.0053, "ack_received": false, "data": " \u00157891212345", "downlink_enable": false, "FCN": "10101", "fragment_size": 12, "send_time": 22.57234, "ack": "", "receiver_abort_received": false, "timeout": 45, "RULE_ID": "00100000", "abort": false, "rssi": -107, "W": "000", "receiver_abort_message": ""}, "8": {"sending_end": 220.8946, "sending_start": 198.3239, "ack_received": false, "data": " \u00166789123456", "downlink_enable": false, "FCN": "10110", "fragment_size": 12, "send_time": 22.57072, "ack": "", "receiver_abort_received": false, "timeout": 45, "RULE_ID": "00100000", "abort": false, "rssi": -107, "W": "000", "receiver_abort_message": ""}, "60": {"sending_end": 1577.623, "sending_start": 1555.053, "ack_received": false, "data": " \u00024567891212", "downlink_enable": false, "FCN": "00010", "fragment_size": 12, "send_time": 22.57019, "ack": "", "receiver_abort_received": false, "timeout": 45, "RULE_ID": "00100000", "abort": false, "rssi": -109, "W": "000", "receiver_abort_message": ""}, "41": {"sending_end": 1076.812, "sending_start": 1054.241, "ack_received": false, "data": " ;2345678912", "downlink_enable": false, "FCN": "11011", "fragment_size": 12, "send_time": 22.57031, "ack": "", "receiver_abort_received": false, "timeout": 45, "RULE_ID": "00100000", "abort": false, "rssi": -107, "W": "001", "receiver_abort_message": ""}, "40": {"sending_end": 1052.107, "sending_start": 1029.536, "ack_received": false, "data": " <3456789121", "downlink_enable": false, "FCN": "11100", "fragment_size": 12, "send_time": 22.57068, "ack": "", "receiver_abort_received": false, "timeout": 45, "RULE_ID": "00100000", "abort": false, "rssi": -107, "W": "001", "receiver_abort_message": ""}, "43": {"sending_end": 1126.229, "sending_start": 1103.657, "ack_received": false, "data": " 92345678912", "downlink_enable": false, "FCN": "11001", "fragment_size": 12, "send_time": 22.57129, "ack": "", "receiver_abort_received": false, "timeout": 45, "RULE_ID": "00100000", "abort": false, "rssi": -107, "W": "001", "receiver_abort_message": ""}}, "tx_status_ok": true}