{"fragmentation_time": 0.1016433, "payload_size": 77, "total_transmission_time": 51.82123, "total_number_of_fragments": 6, "fragments": {"4": {"abort": false, "timeout": 0, "W": "00", "send_time": 2.636429, "rssi": 0, "data": "\u000212345678912", "sending_start": 144.5355, "receiver_abort_received": false, "receiver_abort_message": "", "RULE_ID": "00", "sending_end": 147.1719, "downlink_enable": false, "ack_received": false, "ack": "", "FCN": "010", "fragment_size": 12}, "5": {"abort": false, "timeout": 0, "W": "00", "send_time": 2.572128, "rssi": 0, "data": "\u000112345678912", "sending_start": 167.3037, "receiver_abort_received": false, "receiver_abort_message": "", "RULE_ID": "00", "sending_end": 169.8758, "downlink_enable": false, "ack_received": false, "ack": "", "FCN": "001", "fragment_size": 12}, "1": {"abort": false, "timeout": 0, "W": "00", "send_time": 2.572662, "rssi": 0, "data": "\u000512345678912", "sending_start": 75.37906, "receiver_abort_received": false, "receiver_abort_message": "", "RULE_ID": "00", "sending_end": 77.95172, "downlink_enable": false, "ack_received": false, "ack": "", "FCN": "101", "fragment_size": 12}, "0": {"abort": false, "timeout": 0, "W": "00", "send_time": 2.573204, "rssi": 0, "data": "\u000612345678912", "sending_start": 52.67491, "receiver_abort_received": false, "receiver_abort_message": "", "RULE_ID": "00", "sending_end": 55.24812, "downlink_enable": false, "ack_received": false, "ack": "", "FCN": "110", "fragment_size": 12}, "3": {"abort": false, "timeout": 0, "W": "00", "send_time": 3.573158, "rssi": 0, "data": "\u000312345678912", "sending_start": 120.809, "receiver_abort_received": false, "receiver_abort_message": "", "RULE_ID": "00", "sending_end": 124.3822, "downlink_enable": false, "ack_received": false, "ack": "", "FCN": "011", "fragment_size": 12}, "2": {"abort": false, "timeout": 0, "W": "00", "send_time": 2.575974, "rssi": 0, "data": "\u000412345678912", "sending_start": 98.10171, "receiver_abort_received": false, "receiver_abort_message": "", "RULE_ID": "00", "sending_end": 100.6777, "downlink_enable": false, "ack_received": false, "ack": "", "FCN": "100", "fragment_size": 12}}, "tx_status_ok": false}